Metadata-Version: 1.0
Name: SmartVentilator
Version: 1.0
Summary: Test module
Home-page: UNKNOWN
Author: Baguette Division
Author-email: baguette@mara.com
License: UNKNOWN
Keywords: proof of concept,learning
Platform: UNKNOWN
